databricks/__init__.py
databricks/model_training/__init__.py
databricks/model_training/version.py
databricks/model_training/api/__init__.py
databricks/model_training/api/exceptions.py
databricks/model_training/api/utils.py
databricks/model_training/api/validation.py
databricks/model_training/api/engine/__init__.py
databricks/model_training/api/engine/engine.py
databricks/model_training/api/foundation_model/__init__.py
databricks/model_training/api/foundation_model/cancel.py
databricks/model_training/api/foundation_model/create.py
databricks/model_training/api/foundation_model/get.py
databricks/model_training/api/foundation_model/get_checkpoints.py
databricks/model_training/api/foundation_model/get_events.py
databricks/model_training/api/foundation_model/get_models.py
databricks/model_training/api/foundation_model/list.py
databricks/model_training/types/__init__.py
databricks/model_training/types/common.py
databricks/model_training/types/run_status.py
databricks/model_training/types/train_config.py
databricks/model_training/types/training_constants.py
databricks/model_training/types/training_run.py
databricks_genai/__init__.py
databricks_genai-1.1.8.dist-info/METADATA
databricks_genai-1.1.8.dist-info/WHEEL
databricks_genai-1.1.8.dist-info/top_level.txt
databricks_genai-1.1.8.dist-info/RECORD
